amieclient/__init__.py
amieclient/client.py
amieclient/packet/__init__.py
amieclient/packet/account.py
amieclient/packet/base.py
amieclient/packet/inform.py
amieclient/packet/packetlist.py
amieclient/packet/person.py
amieclient/packet/project.py
amieclient/packet/user.py
amieclient/packet/validators.py
amieclient/test/__init__.py
amieclient/test/fixtures.py
amieclient/test/test_client.py
amieclient/test/test_packet.py
amieclient/transaction/__init__.py
amieclient/usage/__init__.py
amieclient/usage/message.py
amieclient/usage/record.py
amieclient/usage/response.py
amieclient-0.6.1.dist-info/LICENSE.txt
amieclient-0.6.1.dist-info/METADATA
amieclient-0.6.1.dist-info/NOTICE
amieclient-0.6.1.dist-info/WHEEL
amieclient-0.6.1.dist-info/top_level.txt
amieclient-0.6.1.dist-info/RECORD
