Metadata-Version: 2.1
Name: amieclient
Version: 0.6.1
Summary: Library for the XSEDE AMIE REST API.
Author: G. Ryan Sablosky
Author-email: sablosky@psc.edu
License: Apache Software License v2.0
Project-URL: Documentation & Examples, https://xsede.github.io/amieclient/
Project-URL: Source, https://github.com/xsede/amieclient/
Project-URL: Tracker, https://github.com/xsede/amieclient/issues
Platform: UNKNOWN
Classifier: License :: OSI Approved :: Apache Software License
Classifier: Development Status :: 4 - Beta
Classifier: Programming Language :: Python :: 3
Classifier: Programming Language :: Python :: 3.5
Classifier: Programming Language :: Python :: 3.6
Classifier: Programming Language :: Python :: 3.7
Classifier: Programming Language :: Python :: 3.8
Classifier: Programming Language :: Python :: 3.9
Requires-Python: >=3.5,<3.10
License-File: LICENSE.txt
License-File: NOTICE
Requires-Dist: requests (<3,>=2.20.0)
Requires-Dist: python-dateutil (<2.7,>=2.6.1) ; python_version < "3.7"
Requires-Dist: python-dateutil (<2.9,>=2.8.1) ; python_version >= "3.7"
Provides-Extra: tests
Requires-Dist: requests-mock (<1.10.0,>=1.9.3) ; extra == 'tests'
